scrapyd_egg_checksum/__init__.py
scrapyd_egg_checksum/eggstorage.py
scrapyd_egg_checksum/webservice.py
scrapyd_egg_checksum-0.1.2.dist-info/LICENSE
scrapyd_egg_checksum-0.1.2.dist-info/METADATA
scrapyd_egg_checksum-0.1.2.dist-info/WHEEL
scrapyd_egg_checksum-0.1.2.dist-info/top_level.txt
scrapyd_egg_checksum-0.1.2.dist-info/RECORD
