Metadata-Version: 2.1
Name: scrapyd-egg-checksum
Version: 0.1.2
Summary: Get the checksum of eggs in case of building distributed scrapy clusters
Home-page: https://github.com/ChristianYeah/scrapyd-egg-checksum
Author: Xiaodong Ye
Author-email: 470504024@qq.com
License: MIT
Platform: UNKNOWN
Classifier: License :: OSI Approved :: MIT License
Classifier: Programming Language :: Python :: 3
Requires-Dist: scrapy
Requires-Dist: scrapyd
